[
	{
		"__TYPE__": "SharedSliceContent",
		"variation": "default",
		"primary": {
			"title": {
				"__TYPE__": "StructuredTextContent",
				"value": [
					{
						"type": "heading2",
						"content": {
							"text": "Build a website that keeps getting better",
							"spans": []
						},
						"direction": "ltr"
					}
				]
			},
			"eyebrowHeadline": {
				"__TYPE__": "FieldContent",
				"type": "Text",
				"value": "Hero"
			},
			"description": {
				"__TYPE__": "StructuredTextContent",
				"value": [
					{
						"type": "paragraph",
						"content": {
							"text": "Learn how prismic.io helps thousands of businesses around the world with some of our customers’ use-cases",
							"spans": []
						},
						"direction": "ltr"
					}
				]
			},
			"image": {
				"url": "https://images.unsplash.com/photo-1584559582128-b8be739912e1?crop=entropy&cs=srgb&fm=jpg&ixid=M3wzMzc0NjN8MHwxfHNlYXJjaHw5fHxmcnVpdHxlbnwwfHx8fDE2OTQ0NDI5NzZ8MA&ixlib=rb-4.0.3&q=85",
				"origin": {
					"id": "h5yMpgOI5nI",
					"url": "https://images.unsplash.com/photo-1584559582128-b8be739912e1?crop=entropy&cs=srgb&fm=jpg&ixid=M3wzMzc0NjN8MHwxfHNlYXJjaHw5fHxmcnVpdHxlbnwwfHx8fDE2OTQ0NDI5NzZ8MA&ixlib=rb-4.0.3&q=85",
					"width": 3710,
					"height": 3710
				},
				"width": 3710,
				"height": 3710,
				"edit": {
					"background": "transparent",
					"zoom": 1,
					"crop": {
						"x": 0,
						"y": 0
					}
				},
				"credits": null,
				"alt": "Image Content",
				"__TYPE__": "ImageContent",
				"thumbnails": {}
			},
			"callToActionLabel": {
				"__TYPE__": "FieldContent",
				"type": "Text",
				"value": "Call to Action"
			},
			"callToActionLink": {
				"__TYPE__": "LinkContent",
				"value": {
					"__TYPE__": "ExternalLink",
					"url": "https://prismic.io"
				}
			},
			"reverse": {
				"__TYPE__": "BooleanContent",
				"value": false
			}
		},
		"items": []
	},
	{
		"__TYPE__": "SharedSliceContent",
		"variation": "fullImage",
		"primary": {
			"eyebrowHeadline": {
				"__TYPE__": "FieldContent",
				"value": "drawn",
				"type": "Text"
			},
			"title": {
				"__TYPE__": "StructuredTextContent",
				"value": [
					{
						"type": "heading1",
						"content": {
							"text": "Finest"
						}
					}
				]
			},
			"description": {
				"__TYPE__": "StructuredTextContent",
				"value": [
					{
						"type": "paragraph",
						"content": {
							"text": "Nisi non ex pariatur ad pariatur consequat nisi do aute officia eiusmod ut nisi occaecat qui. Ullamco aute Lorem eiusmod cupidatat nostrud est cillum proident aliqua pariatur est officia exercitation magna ullamco. Commodo aliquip irure nulla fugiat eiusmod eu."
						}
					}
				]
			},
			"image": {
				"origin": {
					"id": "main",
					"url": "https://images.unsplash.com/photo-1515378960530-7c0da6231fb1",
					"width": 5616,
					"height": 3744
				},
				"url": "https://images.unsplash.com/photo-1515378960530-7c0da6231fb1",
				"width": 5616,
				"height": 3744,
				"edit": {
					"zoom": 1,
					"crop": {
						"x": 0,
						"y": 0
					},
					"background": "transparent"
				},
				"credits": null,
				"alt": null,
				"__TYPE__": "ImageContent",
				"thumbnails": {}
			},
			"callToActionLabel": {
				"__TYPE__": "FieldContent",
				"value": "riding",
				"type": "Text"
			},
			"callToActionLink": {
				"__TYPE__": "LinkContent",
				"value": {
					"__TYPE__": "ExternalLink",
					"url": "http://twitter.com"
				}
			},
			"reverse": {
				"__TYPE__": "BooleanContent",
				"value": false
			}
		},
		"items": [
			{
				"__TYPE__": "GroupItemContent",
				"value": []
			}
		]
	}
]